[{"dependency":"@parcel/transformer-sass","drift":0,"pulse":0.06023395415374717,"releases":0,"major":0,"minor":0,"patch":0},{"dependency":"bootstrap","drift":0,"pulse":0.3395004688665749,"releases":0,"major":0,"minor":0,"patch":0},{"dependency":"chai","drift":0,"pulse":0.016427442041931046,"releases":0,"major":0,"minor":0,"patch":0},{"dependency":"chart.js","drift":0,"pulse":0.20808093253112658,"releases":0,"major":0,"minor":0,"patch":0},{"dependency":"datatables.net-bs","drift":0,"pulse":0.013689535034942538,"releases":0,"major":0,"minor":0,"patch":0},{"dependency":"libyear","drift":0,"pulse":0.30664558478271287,"releases":0,"major":0,"minor":0,"patch":0},{"dependency":"mocha","drift":0,"pulse":0.08487511721664373,"releases":0,"major":0,"minor":0,"patch":0},{"dependency":"p-limit","drift":0,"pulse":0.19165349048919553,"releases":0,"major":0,"minor":0,"patch":0},{"dependency":"parcel","drift":0,"pulse":0.06023395415374717,"releases":0,"major":0,"minor":0,"patch":0},{"dependency":"preferred-pm","drift":0,"pulse":0.900771405299219,"releases":0,"major":0,"minor":0,"patch":0},{"dependency":"semver","drift":0,"pulse":0.2245083745730576,"releases":0,"major":0,"minor":0,"patch":0},{"dependency":"simple-git","drift":0,"pulse":0.15332279239135643,"releases":0,"major":0,"minor":0,"patch":0},{"dependency":"sinon","drift":0,"pulse":0.024641163062896567,"releases":0,"major":0,"minor":0,"patch":0}]