[{"dependency":"@parcel/transformer-sass","drift":0,"pulse":0.12046790830749433,"releases":0,"major":0,"minor":0,"patch":0},{"dependency":"bootstrap","drift":0,"pulse":0.3997344230203221,"releases":0,"major":0,"minor":0,"patch":0},{"dependency":"chai","drift":0,"pulse":0.07666139619567822,"releases":0,"major":0,"minor":0,"patch":0},{"dependency":"chart.js","drift":0,"pulse":0.26831488668487374,"releases":0,"major":0,"minor":0,"patch":0},{"dependency":"datatables.net-bs","drift":0,"pulse":0.07392348918868971,"releases":0,"major":0,"minor":0,"patch":0},{"dependency":"libyear","drift":0,"pulse":0.36687953893646,"releases":0,"major":0,"minor":0,"patch":0},{"dependency":"mocha","drift":0,"pulse":0.008213721020965523,"releases":0,"major":0,"minor":0,"patch":0},{"dependency":"p-limit","drift":0,"pulse":0.2518874446429427,"releases":0,"major":0,"minor":0,"patch":0},{"dependency":"parcel","drift":0,"pulse":0.12046790830749433,"releases":0,"major":0,"minor":0,"patch":0},{"dependency":"preferred-pm","drift":0,"pulse":0.9610053594529662,"releases":0,"major":0,"minor":0,"patch":0},{"dependency":"semver","drift":0,"pulse":0.28474232872680477,"releases":0,"major":0,"minor":0,"patch":0},{"dependency":"simple-git","drift":0,"pulse":0.2135567465451036,"releases":0,"major":0,"minor":0,"patch":0},{"dependency":"sinon","drift":0,"pulse":0.08487511721664373,"releases":0,"major":0,"minor":0,"patch":0}]